MANIFEST.in
ez_setup.py
setup.py
bshell/__init__.py
bshell/__init__.pyc
bshell/management/__init__.py
bshell/management/__init__.pyc
bshell/management/commands/__init__.py
bshell/management/commands/bshell.py
django_bshell.egg-info/PKG-INFO
django_bshell.egg-info/SOURCES.txt
django_bshell.egg-info/dependency_links.txt
django_bshell.egg-info/top_level.txt