Metadata-Version: 1.0
Name: django-bshell
Version: 1.0.1
Summary: Django management command to run bshell, and import all models
Home-page: http://bitbucket.org/schinckel/django-bpython/
Author: Matthew Schinckel
Author-email: matt@schinckel.net
License: UNKNOWN
Platform: UNKNOWN
